{
	"identifier": {
		"identifier": "10.25039/CIE.DS.bfn2eqci",
		"identifierType": "DOI"
	},
	"creators": [
		{
			"name": "International Commission on Illumination (CIE)",
			"nameType": "Organizational"
		}
	],
	"titles": [
		{
			"title": "CIE spectral luminous efficiency for 10° photopic vision"
		}
	],
	"publisher": "International Commission on Illumination (CIE), Vienna, AT",
	"publicationYear": "2019",
	"subjects": [
		{
			"subject": "Photometry"
		},
		{
			"subject": "Objective photometry"
		},
		{
			"subject": "Units. Constants"
		}
	],
	"language": "en",
	"alternateIdentifiers": [
		{
			"alternateIdentifier": "CIE_sle_10deg.csv",
			"alternateIdentifierType": "fileName"
		}
	],
	"relatedItems": [
		{
			"relatedItemIdentifier": "10.25039/tr.018.2019",
			"relatedItemIdentifierType": "DOI",
			"relationType": "IsPartOf",
			"relatedItemType": "Report",
			"titles": [
				"CIE 018:2019 The Basis of Physical Photometry, 3rd Edition"
			]
		}
	],
	"formats": [
		"text/csv"
	],
	"types": {
		"resourceType": "dataTable",
		"resourceTypeGeneral": "Dataset"
	},
	"descriptions": [
		{
			"description": "Values of spectral luminous efficiency for 10° photopic vision, V10(lambda), lambda in standard air, original source: CIE 018:2019, Table 5",
			"descriptionType": "Abstract"
		}
	],
	"rightsList": [
		{
			"rights": "Creative Commons Attribution-ShareAlike 4.0 International",
			"rightsURI": "https://creativecommons.org/licenses/by-sa/4.0/",
			"rightsIdentifier": "CC BY-SA 4.0"
		}
	],
	"checksums": [
		{
			"hashMethod": "md5",
			"checksum": "b702e2c81f87115f151e9e0603925834"
		},
		{
			"hashMethod": "sha256",
			"checksum": "e67ec48406bdb6cef7ce03c42bd66f9dfc8601fb0a60837f8971973d4b960c9"
		}
	],
	"datatableInfo": {
		"validations": [
			{
				"validationType": "sumOfColumns",
				"validationValue": "[280245,116.661877102312]"
			},
			{
				"validationType": "sampleRow",
				"validationParameter": "120",
				"validationValue": "479,0.245997000000"
			}
		],
		"interpolationMethod": "linear",
		"extrapolationMethod": "zero",
		"dataQuality": "nominal",
		"columnHeaders": [
			{
				"title": "lambda",
				"unit": "nm",
				"quantity": "wavelength",
				"wavelength_first": 360,
				"wavelength_last": 830,
				"wavelength_step": 1
			},
			{
				"title": "V_10(lambda)",
				"unit": "dimensionless",
				"quantity": "spectral luminous efficiency",
				"wavelength_first": 360,
				"wavelength_last": 830,
				"wavelength_step": 1
			}
		]
	},
	"schemaName": "CIEmetaDigitalProduct",
	"schemaVersion": 4,
	"schemaURL": "https://doi.org/10.25039/CIE.SC.4taqevcd"
}